csrc/common.h
csrc/dequant_impl_packed.cu
csrc/ops.cc
csrc/utils.cuh
tests/test_weight_quantizer.py
tools/absorb_perm.py
tools/eval.py
vptq/__init__.py
vptq/__main__.py
vptq/app.py
vptq/app_gpu.py
vptq/app_utils.py
vptq/layer_quantizer.py
vptq/ops.cpython-310-x86_64-linux-gnu.so
vptq/quantize_executer.py
vptq/quantizer.py
vptq/vptq.py
vptq/weight_quantizer.py
vptq/layers/__init__.py
vptq/layers/model_base.py
vptq/layers/vqlinear.py
vptq/models/llama.py
vptq/models/mistral.py
vptq/models/nvembed.py
vptq/models/phi.py
vptq/models/qwen.py
vptq/utils/config.py
vptq/utils/data.py
vptq/utils/hessian.py
vptq/utils/layer_utils.py
vptq/utils/log.py
vptq/utils/pack.py
vptq/utils/reshape.py
vptq/utils/sign.py
vptq_aqua-0.0.4.dist-info/LICENSE
vptq_aqua-0.0.4.dist-info/METADATA
vptq_aqua-0.0.4.dist-info/WHEEL
vptq_aqua-0.0.4.dist-info/top_level.txt
vptq_aqua-0.0.4.dist-info/RECORD
