Metadata-Version: 2.1
Name: vptq-aqua
Version: 0.0.4
Summary: UNKNOWN
Home-page: UNKNOWN
License: UNKNOWN
Platform: UNKNOWN
Requires-Python: >=3.8
License-File: LICENSE
Requires-Dist: datasets
Requires-Dist: torch
Requires-Dist: transformers>=4.45
Requires-Dist: safetensors
Requires-Dist: psutil
Requires-Dist: accelerate
Requires-Dist: gradio
Requires-Dist: plotly==5.9.0
Requires-Dist: pynvml
